ipakyuli/__init__.py
ipakyuli/exception.py
ipakyuli/integration.py
ipakyuli/transfer.py
ipakyuli-0.1.0.dist-info/LICENSE
ipakyuli-0.1.0.dist-info/METADATA
ipakyuli-0.1.0.dist-info/WHEEL
ipakyuli-0.1.0.dist-info/top_level.txt
ipakyuli-0.1.0.dist-info/RECORD
