Metadata-Version: 2.1
Name: ipakyuli
Version: 0.1.0
Summary: A brief description
Home-page: https://github.com/islombeknv/ipakyulibank.git
Author: Bank Transaction
Author-email: islomjon2702@gmail.com
Classifier: Programming Language :: Python :: 3
Classifier: License :: OSI Approved :: MIT License
Classifier: Operating System :: OS Independent
Requires-Python: >=3.6
License-File: LICENSE
